PSTHM/__init__.py
PSTHM/kernels.py
PSTHM/load.py
PSTHM/model.py
PSTHM/opti.py
PSTHM/plotting.py
PSTHM/post.py
PaleoSTeHM-1.0.0.dist-info/LICENSE
PaleoSTeHM-1.0.0.dist-info/METADATA
PaleoSTeHM-1.0.0.dist-info/WHEEL
PaleoSTeHM-1.0.0.dist-info/top_level.txt
PaleoSTeHM-1.0.0.dist-info/RECORD
