Metadata-Version: 2.2
Name: PaleoSTeHM
Version: 1.0.0
Summary: A modern, scalable Spatio-Temporal Hierarchical Modeling framework for paleo-environmental data
Home-page: https://paleostehm.org/
Author: Yucheng Lin
Author-email: snqz1358@gmail.com
License: MIT
Project-URL: Homepage, https://paleostehm.org/
Project-URL: Source, https://github.com/radical-collaboration/PaleoSTeHM
Project-URL: Tracker, https://github.com/radical-collaboration/PaleoSTeHM/issues
Keywords: paleoenviromental,spatio-temporal,hierarchical modeling
Classifier: Programming Language :: Python :: 3
Classifier: License :: OSI Approved :: MIT License
Classifier: Operating System :: OS Independent
Classifier: Development Status :: 5 - Production/Stable
Requires-Python: >=3.7
License-File: LICENSE
Requires-Dist: sphinx_copybutton
Requires-Dist: sphinx-rtd-theme
Requires-Dist: cartopy
Requires-Dist: matplotlib
Requires-Dist: numpy
Requires-Dist: torch==2.3.1
Requires-Dist: pandas==1.3.4
Requires-Dist: scipy
Requires-Dist: pyro-ppl
Requires-Dist: tqdm==4.62.3
Requires-Dist: seaborn==0.11.2
Requires-Dist: statsmodels==0.14.0
Requires-Dist: astropy
Requires-Dist: openpyxl
Requires-Dist: jupyter==1.0.0
Requires-Dist: ipywidgets
Requires-Dist: netcdf4==1.6.5
Requires-Dist: ipykernel
Requires-Dist: nmmn
Requires-Dist: pip==21.2.4
Dynamic: author
Dynamic: author-email
Dynamic: classifier
Dynamic: description
Dynamic: description-content-type
Dynamic: home-page
Dynamic: keywords
Dynamic: license
Dynamic: project-url
Dynamic: requires-dist
Dynamic: requires-python
Dynamic: summary
